bluesky_hwproxy/__init__.py
bluesky_hwproxy/_device.py
bluesky_hwproxy/_proxy.py
bluesky_hwproxy/hwproxy_cli.py
bluesky_hwproxy/hwproxy_server.py
bluesky_hwproxy/comms/__init__.py
bluesky_hwproxy-2022.8.0.dist-info/entry_points.txt
bluesky_hwproxy-2022.8.0.dist-info/LICENSE
bluesky_hwproxy-2022.8.0.dist-info/WHEEL
bluesky_hwproxy-2022.8.0.dist-info/METADATA
bluesky_hwproxy-2022.8.0.dist-info/RECORD
