Metadata-Version: 2.1
Name: bluesky-hwproxy
Version: 2022.8.0
Summary: Proxy for reading bluesky hardware over ZMQ interface.
Author-email: Kyle Sunden <contact@ksunden.space>
Requires-Python: >=3.7
Requires-Dist: rich
Requires-Dist: click
Requires-Dist: bluesky-queueserver
Requires-Dist: pyzmq
Requires-Dist: bluesky>=1.9.0
